fastedit/Composing.py
fastedit/Errors.py
fastedit/Medias.py
fastedit/Overlays.py
fastedit/__init__.py
fastedit/utils.py
tests/__init__.py
tests/integration/__init__.py
tests/integration/audio_test.py
tests/integration/video_test.py
tests/unit/__init__.py
tests/unit/audio_test.py
tests/unit/composing_test.py
tests/unit/image_test.py
tests/unit/media_test.py
tests/unit/video_test.py
fastedit-0.7.0.dist-info/LICENSE
fastedit-0.7.0.dist-info/METADATA
fastedit-0.7.0.dist-info/WHEEL
fastedit-0.7.0.dist-info/top_level.txt
fastedit-0.7.0.dist-info/RECORD
