Metadata-Version: 2.1
Name: fastedit
Version: 0.7.0
Summary: A simple python library to edit videos
Home-page: https://github.com/ThomasMargnac/fastedit
Author: Thomas Margnac
License: Apache License 2.0
Project-URL: Bug Tracker, https://github.com/ThomasMargnac/fastedit/issues
Project-URL: Wiki, https://github.com/ThomasMargnac/fastedit/wiki
Project-URL: API Documentation, https://thomasmargnac.github.io/fastedit/
Keywords: video,editing
Classifier: Programming Language :: Python :: 3.7
Classifier: Programming Language :: Python :: 3.8
Classifier: Programming Language :: Python :: 3.9
Classifier: Programming Language :: Python :: 3.10
Classifier: Programming Language :: Python :: 3.11
Classifier: License :: OSI Approved :: Apache Software License
License-File: LICENSE
Provides-Extra: dev
Requires-Dist: pytest (==7.2.0) ; extra == 'dev'
